[{"arguments":["clang","-Wno-documentation-unknown-command","-Wno-unknown-warning-option","-Wno-unknown-pragmas","-nostdinc","-nostdinc++","-g","-Wall","-Wextra","-Wextra","-fexceptions","-mthreads","-fsyntax-only","-m64","--target=x86_64-w64-mingw32","-std=gnu++17","-DUNICODE","-D_UNICODE","-DWIN32","-DMINGW_HAS_SECURE_API","-DQT_DEPRECATED_WARNINGS","-DQT_QML_DEBUG","-DQT_WIDGETS_LIB","-DQT_GUI_LIB","-DQT_CORE_LIB","-DQT_NEEDS_QMAIN","-DQ_CREATOR_RUN","-DQT_ANNOTATE_FUNCTION(x)=__attribute__((annotate(#x)))","-ID:\\Qt\\Tools\\QtCreator\\share\\qtcreator\\cplusplus\\wrappedMingwHeaders","-ID:\\Qt\\Tools\\QtCreator\\share\\qtcreator\\cplusplus\\wrappedQtHeaders","-ID:\\Qt\\Tools\\QtCreator\\share\\qtcreator\\cplusplus\\wrappedQtHeaders\\QtCore","-ID:\\software\\flyBrid","-ID:\\Qt\\6.10.1\\mingw_64\\include","-ID:\\Qt\\6.10.1\\mingw_64\\include\\QtWidgets","-ID:\\Qt\\6.10.1\\mingw_64\\include\\QtGui","-ID:\\Qt\\6.10.1\\mingw_64\\include\\QtCore","-ID:\\software\\flyBrid\\build\\Desktop_Qt_6_10_1_MinGW_64_bit-Debug\\debug","-ID:\\software\\flyBrid\\build\\Desktop_Qt_6_10_1_MinGW_64_bit-Debug","-ID:\\Qt\\6.10.1\\mingw_64\\mkspecs\\win32-g++","-I\\include","-isystem","D:\\Qt\\Tools\\mingw1310_64\\lib\\gcc\\x86_64-w64-mingw32\\13.1.0\\include\\c++","-isystem","D:\\Qt\\Tools\\mingw1310_64\\lib\\gcc\\x86_64-w64-mingw32\\13.1.0\\include\\c++\\x86_64-w64-mingw32","-isystem","D:\\Qt\\Tools\\mingw1310_64\\lib\\gcc\\x86_64-w64-mingw32\\13.1.0\\include\\c++\\backward","-isystem","D:\\Qt\\Tools\\QtCreator\\bin\\clang\\lib\\clang\\21\\include","-isystem","D:\\Qt\\Tools\\mingw1310_64\\x86_64-w64-mingw32\\include","-fmessage-length=0","-fdiagnostics-show-note-include-stack","-fretain-comments-from-system-headers","-fmacro-backtrace-limit=0","-ferror-limit=1000","-x","c++","D:/software/flyBrid/main.cpp"],"directory":"D:/software/flyBrid/build/Desktop_Qt_6_10_1_MinGW_64_bit-Debug/.qtc_clangd","file":"D:/software/flyBrid/main.cpp"},{"arguments":["clang","-Wno-documentation-unknown-command","-Wno-unknown-warning-option","-Wno-unknown-pragmas","-nostdinc","-nostdinc++","-g","-Wall","-Wextra","-Wextra","-fexceptions","-mthreads","-fsyntax-only","-m64","--target=x86_64-w64-mingw32","-std=gnu++17","-DUNICODE","-D_UNICODE","-DWIN32","-DMINGW_HAS_SECURE_API","-DQT_DEPRECATED_WARNINGS","-DQT_QML_DEBUG","-DQT_WIDGETS_LIB","-DQT_GUI_LIB","-DQT_CORE_LIB","-DQT_NEEDS_QMAIN","-DQ_CREATOR_RUN","-DQT_ANNOTATE_FUNCTION(x)=__attribute__((annotate(#x)))","-ID:\\Qt\\Tools\\QtCreator\\share\\qtcreator\\cplusplus\\wrappedMingwHeaders","-ID:\\Qt\\Tools\\QtCreator\\share\\qtcreator\\cplusplus\\wrappedQtHeaders","-ID:\\Qt\\Tools\\QtCreator\\share\\qtcreator\\cplusplus\\wrappedQtHeaders\\QtCore","-ID:\\software\\flyBrid","-ID:\\Qt\\6.10.1\\mingw_64\\include","-ID:\\Qt\\6.10.1\\mingw_64\\include\\QtWidgets","-ID:\\Qt\\6.10.1\\mingw_64\\include\\QtGui","-ID:\\Qt\\6.10.1\\mingw_64\\include\\QtCore","-ID:\\software\\flyBrid\\build\\Desktop_Qt_6_10_1_MinGW_64_bit-Debug\\debug","-ID:\\software\\flyBrid\\build\\Desktop_Qt_6_10_1_MinGW_64_bit-Debug","-ID:\\Qt\\6.10.1\\mingw_64\\mkspecs\\win32-g++","-I\\include","-isystem","D:\\Qt\\Tools\\mingw1310_64\\lib\\gcc\\x86_64-w64-mingw32\\13.1.0\\include\\c++","-isystem","D:\\Qt\\Tools\\mingw1310_64\\lib\\gcc\\x86_64-w64-mingw32\\13.1.0\\include\\c++\\x86_64-w64-mingw32","-isystem","D:\\Qt\\Tools\\mingw1310_64\\lib\\gcc\\x86_64-w64-mingw32\\13.1.0\\include\\c++\\backward","-isystem","D:\\Qt\\Tools\\QtCreator\\bin\\clang\\lib\\clang\\21\\include","-isystem","D:\\Qt\\Tools\\mingw1310_64\\x86_64-w64-mingw32\\include","-fmessage-length=0","-fdiagnostics-show-note-include-stack","-fretain-comments-from-system-headers","-fmacro-backtrace-limit=0","-ferror-limit=1000","-x","c++","D:/software/flyBrid/brid.cpp"],"directory":"D:/software/flyBrid/build/Desktop_Qt_6_10_1_MinGW_64_bit-Debug/.qtc_clangd","file":"D:/software/flyBrid/brid.cpp"},{"arguments":["clang","-Wno-documentation-unknown-command","-Wno-unknown-warning-option","-Wno-unknown-pragmas","-nostdinc","-nostdinc++","-g","-Wall","-Wextra","-Wextra","-fexceptions","-mthreads","-fsyntax-only","-m64","--target=x86_64-w64-mingw32","-std=gnu++17","-DUNICODE","-D_UNICODE","-DWIN32","-DMINGW_HAS_SECURE_API","-DQT_DEPRECATED_WARNINGS","-DQT_QML_DEBUG","-DQT_WIDGETS_LIB","-DQT_GUI_LIB","-DQT_CORE_LIB","-DQT_NEEDS_QMAIN","-DQ_CREATOR_RUN","-DQT_ANNOTATE_FUNCTION(x)=__attribute__((annotate(#x)))","-ID:\\Qt\\Tools\\QtCreator\\share\\qtcreator\\cplusplus\\wrappedMingwHeaders","-ID:\\Qt\\Tools\\QtCreator\\share\\qtcreator\\cplusplus\\wrappedQtHeaders","-ID:\\Qt\\Tools\\QtCreator\\share\\qtcreator\\cplusplus\\wrappedQtHeaders\\QtCore","-ID:\\software\\flyBrid","-ID:\\Qt\\6.10.1\\mingw_64\\include","-ID:\\Qt\\6.10.1\\mingw_64\\include\\QtWidgets","-ID:\\Qt\\6.10.1\\mingw_64\\include\\QtGui","-ID:\\Qt\\6.10.1\\mingw_64\\include\\QtCore","-ID:\\software\\flyBrid\\build\\Desktop_Qt_6_10_1_MinGW_64_bit-Debug\\debug","-ID:\\software\\flyBrid\\build\\Desktop_Qt_6_10_1_MinGW_64_bit-Debug","-ID:\\Qt\\6.10.1\\mingw_64\\mkspecs\\win32-g++","-I\\include","-isystem","D:\\Qt\\Tools\\mingw1310_64\\lib\\gcc\\x86_64-w64-mingw32\\13.1.0\\include\\c++","-isystem","D:\\Qt\\Tools\\mingw1310_64\\lib\\gcc\\x86_64-w64-mingw32\\13.1.0\\include\\c++\\x86_64-w64-mingw32","-isystem","D:\\Qt\\Tools\\mingw1310_64\\lib\\gcc\\x86_64-w64-mingw32\\13.1.0\\include\\c++\\backward","-isystem","D:\\Qt\\Tools\\QtCreator\\bin\\clang\\lib\\clang\\21\\include","-isystem","D:\\Qt\\Tools\\mingw1310_64\\x86_64-w64-mingw32\\include","-fmessage-length=0","-fdiagnostics-show-note-include-stack","-fretain-comments-from-system-headers","-fmacro-backtrace-limit=0","-ferror-limit=1000","-x","c++","D:/software/flyBrid/game.cpp"],"directory":"D:/software/flyBrid/build/Desktop_Qt_6_10_1_MinGW_64_bit-Debug/.qtc_clangd","file":"D:/software/flyBrid/game.cpp"},{"arguments":["clang","-Wno-documentation-unknown-command","-Wno-unknown-warning-option","-Wno-unknown-pragmas","-nostdinc","-nostdinc++","-g","-Wall","-Wextra","-Wextra","-fexceptions","-mthreads","-fsyntax-only","-m64","--target=x86_64-w64-mingw32","-std=gnu++17","-DUNICODE","-D_UNICODE","-DWIN32","-DMINGW_HAS_SECURE_API","-DQT_DEPRECATED_WARNINGS","-DQT_QML_DEBUG","-DQT_WIDGETS_LIB","-DQT_GUI_LIB","-DQT_CORE_LIB","-DQT_NEEDS_QMAIN","-DQ_CREATOR_RUN","-DQT_ANNOTATE_FUNCTION(x)=__attribute__((annotate(#x)))","-ID:\\Qt\\Tools\\QtCreator\\share\\qtcreator\\cplusplus\\wrappedMingwHeaders","-ID:\\Qt\\Tools\\QtCreator\\share\\qtcreator\\cplusplus\\wrappedQtHeaders","-ID:\\Qt\\Tools\\QtCreator\\share\\qtcreator\\cplusplus\\wrappedQtHeaders\\QtCore","-ID:\\software\\flyBrid","-ID:\\Qt\\6.10.1\\mingw_64\\include","-ID:\\Qt\\6.10.1\\mingw_64\\include\\QtWidgets","-ID:\\Qt\\6.10.1\\mingw_64\\include\\QtGui","-ID:\\Qt\\6.10.1\\mingw_64\\include\\QtCore","-ID:\\software\\flyBrid\\build\\Desktop_Qt_6_10_1_MinGW_64_bit-Debug\\debug","-ID:\\software\\flyBrid\\build\\Desktop_Qt_6_10_1_MinGW_64_bit-Debug","-ID:\\Qt\\6.10.1\\mingw_64\\mkspecs\\win32-g++","-I\\include","-isystem","D:\\Qt\\Tools\\mingw1310_64\\lib\\gcc\\x86_64-w64-mingw32\\13.1.0\\include\\c++","-isystem","D:\\Qt\\Tools\\mingw1310_64\\lib\\gcc\\x86_64-w64-mingw32\\13.1.0\\include\\c++\\x86_64-w64-mingw32","-isystem","D:\\Qt\\Tools\\mingw1310_64\\lib\\gcc\\x86_64-w64-mingw32\\13.1.0\\include\\c++\\backward","-isystem","D:\\Qt\\Tools\\QtCreator\\bin\\clang\\lib\\clang\\21\\include","-isystem","D:\\Qt\\Tools\\mingw1310_64\\x86_64-w64-mingw32\\include","-fmessage-length=0","-fdiagnostics-show-note-include-stack","-fretain-comments-from-system-headers","-fmacro-backtrace-limit=0","-ferror-limit=1000","-x","c++","D:/software/flyBrid/pipe.cpp"],"directory":"D:/software/flyBrid/build/Desktop_Qt_6_10_1_MinGW_64_bit-Debug/.qtc_clangd","file":"D:/software/flyBrid/pipe.cpp"},{"arguments":["clang","-Wno-documentation-unknown-command","-Wno-unknown-warning-option","-Wno-unknown-pragmas","-nostdinc","-nostdinc++","-g","-Wall","-Wextra","-Wextra","-fexceptions","-mthreads","-fsyntax-only","-m64","--target=x86_64-w64-mingw32","-std=gnu++17","-DUNICODE","-D_UNICODE","-DWIN32","-DMINGW_HAS_SECURE_API","-DQT_DEPRECATED_WARNINGS","-DQT_QML_DEBUG","-DQT_WIDGETS_LIB","-DQT_GUI_LIB","-DQT_CORE_LIB","-DQT_NEEDS_QMAIN","-DQ_CREATOR_RUN","-DQT_ANNOTATE_FUNCTION(x)=__attribute__((annotate(#x)))","-ID:\\Qt\\Tools\\QtCreator\\share\\qtcreator\\cplusplus\\wrappedMingwHeaders","-ID:\\Qt\\Tools\\QtCreator\\share\\qtcreator\\cplusplus\\wrappedQtHeaders","-ID:\\Qt\\Tools\\QtCreator\\share\\qtcreator\\cplusplus\\wrappedQtHeaders\\QtCore","-ID:\\software\\flyBrid","-ID:\\Qt\\6.10.1\\mingw_64\\include","-ID:\\Qt\\6.10.1\\mingw_64\\include\\QtWidgets","-ID:\\Qt\\6.10.1\\mingw_64\\include\\QtGui","-ID:\\Qt\\6.10.1\\mingw_64\\include\\QtCore","-ID:\\software\\flyBrid\\build\\Desktop_Qt_6_10_1_MinGW_64_bit-Debug\\debug","-ID:\\software\\flyBrid\\build\\Desktop_Qt_6_10_1_MinGW_64_bit-Debug","-ID:\\Qt\\6.10.1\\mingw_64\\mkspecs\\win32-g++","-I\\include","-isystem","D:\\Qt\\Tools\\mingw1310_64\\lib\\gcc\\x86_64-w64-mingw32\\13.1.0\\include\\c++","-isystem","D:\\Qt\\Tools\\mingw1310_64\\lib\\gcc\\x86_64-w64-mingw32\\13.1.0\\include\\c++\\x86_64-w64-mingw32","-isystem","D:\\Qt\\Tools\\mingw1310_64\\lib\\gcc\\x86_64-w64-mingw32\\13.1.0\\include\\c++\\backward","-isystem","D:\\Qt\\Tools\\QtCreator\\bin\\clang\\lib\\clang\\21\\include","-isystem","D:\\Qt\\Tools\\mingw1310_64\\x86_64-w64-mingw32\\include","-fmessage-length=0","-fdiagnostics-show-note-include-stack","-fretain-comments-from-system-headers","-fmacro-backtrace-limit=0","-ferror-limit=1000","-x","c++-header","D:/software/flyBrid/game.h"],"directory":"D:/software/flyBrid/build/Desktop_Qt_6_10_1_MinGW_64_bit-Debug/.qtc_clangd","file":"D:/software/flyBrid/game.h"},{"arguments":["clang","-Wno-documentation-unknown-command","-Wno-unknown-warning-option","-Wno-unknown-pragmas","-nostdinc","-nostdinc++","-g","-Wall","-Wextra","-Wextra","-fexceptions","-mthreads","-fsyntax-only","-m64","--target=x86_64-w64-mingw32","-std=gnu++17","-DUNICODE","-D_UNICODE","-DWIN32","-DMINGW_HAS_SECURE_API","-DQT_DEPRECATED_WARNINGS","-DQT_QML_DEBUG","-DQT_WIDGETS_LIB","-DQT_GUI_LIB","-DQT_CORE_LIB","-DQT_NEEDS_QMAIN","-DQ_CREATOR_RUN","-DQT_ANNOTATE_FUNCTION(x)=__attribute__((annotate(#x)))","-ID:\\Qt\\Tools\\QtCreator\\share\\qtcreator\\cplusplus\\wrappedMingwHeaders","-ID:\\Qt\\Tools\\QtCreator\\share\\qtcreator\\cplusplus\\wrappedQtHeaders","-ID:\\Qt\\Tools\\QtCreator\\share\\qtcreator\\cplusplus\\wrappedQtHeaders\\QtCore","-ID:\\software\\flyBrid","-ID:\\Qt\\6.10.1\\mingw_64\\include","-ID:\\Qt\\6.10.1\\mingw_64\\include\\QtWidgets","-ID:\\Qt\\6.10.1\\mingw_64\\include\\QtGui","-ID:\\Qt\\6.10.1\\mingw_64\\include\\QtCore","-ID:\\software\\flyBrid\\build\\Desktop_Qt_6_10_1_MinGW_64_bit-Debug\\debug","-ID:\\software\\flyBrid\\build\\Desktop_Qt_6_10_1_MinGW_64_bit-Debug","-ID:\\Qt\\6.10.1\\mingw_64\\mkspecs\\win32-g++","-I\\include","-isystem","D:\\Qt\\Tools\\mingw1310_64\\lib\\gcc\\x86_64-w64-mingw32\\13.1.0\\include\\c++","-isystem","D:\\Qt\\Tools\\mingw1310_64\\lib\\gcc\\x86_64-w64-mingw32\\13.1.0\\include\\c++\\x86_64-w64-mingw32","-isystem","D:\\Qt\\Tools\\mingw1310_64\\lib\\gcc\\x86_64-w64-mingw32\\13.1.0\\include\\c++\\backward","-isystem","D:\\Qt\\Tools\\QtCreator\\bin\\clang\\lib\\clang\\21\\include","-isystem","D:\\Qt\\Tools\\mingw1310_64\\x86_64-w64-mingw32\\include","-fmessage-length=0","-fdiagnostics-show-note-include-stack","-fretain-comments-from-system-headers","-fmacro-backtrace-limit=0","-ferror-limit=1000","-x","c++-header","D:/software/flyBrid/pipe.h"],"directory":"D:/software/flyBrid/build/Desktop_Qt_6_10_1_MinGW_64_bit-Debug/.qtc_clangd","file":"D:/software/flyBrid/pipe.h"},{"arguments":["clang","-Wno-documentation-unknown-command","-Wno-unknown-warning-option","-Wno-unknown-pragmas","-nostdinc","-nostdinc++","-g","-Wall","-Wextra","-Wextra","-fexceptions","-mthreads","-fsyntax-only","-m64","--target=x86_64-w64-mingw32","-std=gnu++17","-DUNICODE","-D_UNICODE","-DWIN32","-DMINGW_HAS_SECURE_API","-DQT_DEPRECATED_WARNINGS","-DQT_QML_DEBUG","-DQT_WIDGETS_LIB","-DQT_GUI_LIB","-DQT_CORE_LIB","-DQT_NEEDS_QMAIN","-DQ_CREATOR_RUN","-DQT_ANNOTATE_FUNCTION(x)=__attribute__((annotate(#x)))","-ID:\\Qt\\Tools\\QtCreator\\share\\qtcreator\\cplusplus\\wrappedMingwHeaders","-ID:\\Qt\\Tools\\QtCreator\\share\\qtcreator\\cplusplus\\wrappedQtHeaders","-ID:\\Qt\\Tools\\QtCreator\\share\\qtcreator\\cplusplus\\wrappedQtHeaders\\QtCore","-ID:\\software\\flyBrid","-ID:\\Qt\\6.10.1\\mingw_64\\include","-ID:\\Qt\\6.10.1\\mingw_64\\include\\QtWidgets","-ID:\\Qt\\6.10.1\\mingw_64\\include\\QtGui","-ID:\\Qt\\6.10.1\\mingw_64\\include\\QtCore","-ID:\\software\\flyBrid\\build\\Desktop_Qt_6_10_1_MinGW_64_bit-Debug\\debug","-ID:\\software\\flyBrid\\build\\Desktop_Qt_6_10_1_MinGW_64_bit-Debug","-ID:\\Qt\\6.10.1\\mingw_64\\mkspecs\\win32-g++","-I\\include","-isystem","D:\\Qt\\Tools\\mingw1310_64\\lib\\gcc\\x86_64-w64-mingw32\\13.1.0\\include\\c++","-isystem","D:\\Qt\\Tools\\mingw1310_64\\lib\\gcc\\x86_64-w64-mingw32\\13.1.0\\include\\c++\\x86_64-w64-mingw32","-isystem","D:\\Qt\\Tools\\mingw1310_64\\lib\\gcc\\x86_64-w64-mingw32\\13.1.0\\include\\c++\\backward","-isystem","D:\\Qt\\Tools\\QtCreator\\bin\\clang\\lib\\clang\\21\\include","-isystem","D:\\Qt\\Tools\\mingw1310_64\\x86_64-w64-mingw32\\include","-fmessage-length=0","-fdiagnostics-show-note-include-stack","-fretain-comments-from-system-headers","-fmacro-backtrace-limit=0","-ferror-limit=1000","-x","c++-header","D:/software/flyBrid/bird.h"],"directory":"D:/software/flyBrid/build/Desktop_Qt_6_10_1_MinGW_64_bit-Debug/.qtc_clangd","file":"D:/software/flyBrid/bird.h"}]